foldergenie/FolderGenie.py
foldergenie/__init__.py
foldergenie/__main__.py
foldergenie-4.0.0.dist-info/METADATA
foldergenie-4.0.0.dist-info/WHEEL
foldergenie-4.0.0.dist-info/entry_points.txt
foldergenie-4.0.0.dist-info/top_level.txt
foldergenie-4.0.0.dist-info/RECORD
