Metadata-Version: 2.1
Name: foldergenie
Version: 4.0.0
Summary: Directory structure creation
Home-page: UNKNOWN
Author: Skadoosh (Hariprasad)
Author-email: <hariprasad19036@gmail.com>
License: MIT
Keywords: python,folder,file,directory,organize
Platform: UNKNOWN
Classifier: License :: OSI Approved :: MIT License
Classifier: Development Status :: 5 - Production/Stable
Classifier: Intended Audience :: Developers
Classifier: Programming Language :: Python :: 3
Classifier: Operating System :: Unix
Classifier: Operating System :: Microsoft :: Windows
